soda_mq/__init__.py
soda_mq/client_factory.py
soda_mq/soda_client.py
soda_mq/soda_consumer.py
soda_mq/soda_producer.py
soda_mq_client-0.1.4.dist-info/LICENSE
soda_mq_client-0.1.4.dist-info/METADATA
soda_mq_client-0.1.4.dist-info/WHEEL
soda_mq_client-0.1.4.dist-info/top_level.txt
soda_mq_client-0.1.4.dist-info/RECORD
