Metadata-Version: 2.1
Name: soda-mq-client
Version: 0.1.4
Summary: SodaMQ客户端库，用于消息队列通信
Author-email: fengb3 <fengb3@gmail.com>
License: MIT
Project-URL: Homepage, https://github.com/fengb3/SodaMQ
Classifier: Programming Language :: Python :: 3
Classifier: License :: OSI Approved :: MIT License
Classifier: Operating System :: OS Independent
Requires-Python: >=3.8
License-File: LICENSE
Requires-Dist: signalrcore==0.9.5
